{
  "2000": {
    "proyectos": [
      {
        "nombreProyecto": "Desarrollo Sistema de Facturación",
        "costoPorMes": {
          "1": 1500,
          "2": 1600,
          "3": 1550,
          "4": 1500,
          "5": 0,
          "6": 0,
          "7": 0,
          "8": 0,
          "9": 0,
          "10": 0,
          "11": 0,
          "12": 0
        },
        "costoTotal": 6150
      },
      {
        "nombreProyecto": "Implementación ERP",
        "costoPorMes": {
          "1": 2000,
          "2": 2100,
          "3": 2050,
          "4": 0,
          "5": 0,
          "6": 0,
          "7": 0,
          "8": 0,
          "9": 0,
          "10": 0,
          "11": 0,
          "12": 0
        },
        "costoTotal": 6150
      }
    ],
    "costoTotalGlobal": 12300
  },
  "2001": {
    "proyectos": [
      {
        "nombreProyecto": "Implementación ERP",
        "costoPorMes": {
          "1": 0,
          "2": 0,
          "3": 0,
          "4": 2200,
          "5": 2250,
          "6": 2300,
          "7": 2400,
          "8": 2500,
          "9": 2600,
          "10": 2700,
          "11": 0,
          "12": 0
        },
        "costoTotal": 16950
      },
      {
        "nombreProyecto": "Migración a Servidores en la Nube",
        "costoPorMes": {
          "1": 3000,
          "2": 3100,
          "3": 3050,
          "4": 0,
          "5": 0,
          "6": 0,
          "7": 0,
          "8": 0,
          "9": 0,
          "10": 0,
          "11": 0,
          "12": 0
        },
        "costoTotal": 9150
      }
    ],
    "costoTotalGlobal": 26100
  },
  "2023": {
    "proyectos": [
      {
        "nombreProyecto": "Desarrollo Plataforma e-Commerce",
        "costoPorMes": {
          "1": 3000,
          "2": 3200,
          "3": 3100,
          "4": 3050,
          "5": 3150,
          "6": 3250,
          "7": 3300,
          "8": 3200,
          "9": 3350,
          "10": 3400,
          "11": 3500,
          "12": 3450
        },
        "costoTotal": 38950
      },
      {
        "nombreProyecto": "Sistema de Gestión de Inventarios",
        "costoPorMes": {
          "1": 3000,
          "2": 3050,
          "3": 3000,
          "4": 2970,
          "5": 3010,
          "6": 3100,
          "7": 3050,
          "8": 3120,
          "9": 3200,
          "10": 3300,
          "11": 3350,
          "12": 3400
        },
        "costoTotal": 37550
      },
      {
        "nombreProyecto": "Implementación Red de Ciberseguridad",
        "costoPorMes": {
          "1": 3500,
          "2": 3600,
          "3": 3550,
          "4": 3520,
          "5": 3450,
          "6": 3400,
          "7": 3480,
          "8": 3550,
          "9": 3600,
          "10": 3700,
          "11": 3750,
          "12": 3800
        },
        "costoTotal": 42900
      }
    ],
    "costoTotalGlobal": 119400
  },
  "2024": {
    "proyectos": [
      {
        "nombreProyecto": "Desarrollo Plataforma e-Commerce",
        "costoPorMes": {
          "1": 3000,
          "2": 3100,
          "3": 3200,
          "4": 0,
          "5": 0,
          "6": 0,
          "7": 0,
          "8": 0,
          "9": 0,
          "10": 0,
          "11": 0,
          "12": 0
        },
        "costoTotal": 9300
      },
      {
        "nombreProyecto": "Rediseño UI/UX Aplicación Móvil",
        "costoPorMes": {
          "1": 2500,
          "2": 2600,
          "3": 2700,
          "4": 2800,
          "5": 2900,
          "6": 3000,
          "7": 3100,
          "8": 3200,
          "9": 0,
          "10": 0,
          "11": 0,
          "12": 0
        },
        "costoTotal": 22800
      }
    ],
    "costoTotalGlobal": 32100
  }
}
